NotebookScripter/NotebookPyFileReader.py
NotebookScripter/__init__.py
NotebookScripter/_main.py
NotebookScripter-6.0.0.dist-info/LICENSE
NotebookScripter-6.0.0.dist-info/METADATA
NotebookScripter-6.0.0.dist-info/WHEEL
NotebookScripter-6.0.0.dist-info/top_level.txt
NotebookScripter-6.0.0.dist-info/RECORD
