Metadata-Version: 2.1
Name: NotebookScripter
Version: 6.0.0
Summary: Expose ipython jupyter notebooks as callable functions.  More info here https://github.com/breathe/NotebookScripter
Home-page: https://github.com/breathe/NotebookScripter
Author: N. Ben Cohen
Author-email: breathevalue@icloud.com
License: MIT
Platform: UNKNOWN
Classifier: License :: OSI Approved :: MIT License
Classifier: Programming Language :: Python :: 3
Classifier: Programming Language :: Python :: 3.6
Classifier: Programming Language :: Python :: Implementation :: CPython
Requires-Dist: ipython
Requires-Dist: nbformat
